{
  "inode" : "1b407535-67e3-4f21-ad00-8ef5ef492d64",
  "identifier" : "8a7d5e23-da1e-420a-b4f0-471e7da8ea2d",
  "aliases" : null,
  "systemHost" : false,
  "siteName" : "default",
  "tagStorage" : "8a7d5e23-da1e-420a-b4f0-471e7da8ea2d",
  "siteThumbnail" : "",
  "runDashboard" : false,
  "keywords" : null,
  "description" : null,
  "googleMap" : null,
  "googleAnalytics" : null,
  "addThis" : null,
  "proxyUrlForEditMode" : null,
  "embeddedDashboard" : null,
  "languageId" : 1,
  "variables" : [ ],
  "modDate" : "2023-05-25T21:56:50.282+00:00",
  "modUser" : "dotcms.org.1",
  "locked" : true,
  "live" : true,
  "default" : true,
  "archived" : false,
  "working" : true,
  "dotCMSObjectType" : "Site"
}